kitconcept/website/__init__.py
kitconcept/website/_types.py
kitconcept/website/configure.zcml
kitconcept/website/dependencies.zcml
kitconcept/website/distributions.zcml
kitconcept/website/handlers.py
kitconcept/website/interfaces.py
kitconcept/website/permissions.zcml
kitconcept/website/profiles.zcml
kitconcept/website/testing.py
kitconcept/website/behaviors/__init__.py
kitconcept/website/behaviors/configure.zcml
kitconcept/website/controlpanels/__init__.py
kitconcept/website/controlpanels/configure.zcml
kitconcept/website/distributions/website/image.png
kitconcept/website/distributions/website/profiles.json
kitconcept/website/distributions/website/schema.json
kitconcept/website/distributions/website/content/discussions.json
kitconcept/website/distributions/website/content/portlets.json
kitconcept/website/distributions/website/content/principals.json
kitconcept/website/distributions/website/content/redirects.json
kitconcept/website/distributions/website/content/relations.json
kitconcept/website/distributions/website/content/translations.json
kitconcept/website/distributions/website/content/content/__metadata__.json
kitconcept/website/distributions/website/content/content/023daca5870d4226871c44317e2840ab/data.json
kitconcept/website/distributions/website/content/content/023daca5870d4226871c44317e2840ab/image/ahmad-ossayli-laJW5pp-6Yw-unsplash.jpg
kitconcept/website/distributions/website/content/content/0c1eaeaca2cc47f48eae213121a6f7a8/data.json
kitconcept/website/distributions/website/content/content/0c1eaeaca2cc47f48eae213121a6f7a8/image/donald-giannatti-Wj1D-qiOseE-unsplash (4).jpg
kitconcept/website/distributions/website/content/content/0e78d2b30abb4d4283068556dc58c9e2/data.json
kitconcept/website/distributions/website/content/content/144516507ac74892b96c1f7b574af7c4/data.json
kitconcept/website/distributions/website/content/content/1e7262f173a54700a5ca2578506b1bc1/data.json
kitconcept_website-2.0.0a6.dist-info/METADATA
kitconcept_website-2.0.0a6.dist-info/WHEEL
kitconcept_website-2.0.0a6.dist-info/entry_points.txt
kitconcept_website-2.0.0a6.dist-info/licenses/LICENSE.GPL
kitconcept_website-2.0.0a6.dist-info/licenses/LICENSE.md
kitconcept_website-2.0.0a6.dist-info/RECORD
